cbutils/__init__.py
cbutils/dateutils.py
cbutils/decorators.py
cbutils/general.py
cbutils/plot.py
cbutils-0.12a0.dist-info/DESCRIPTION.rst
cbutils-0.12a0.dist-info/METADATA
cbutils-0.12a0.dist-info/RECORD
cbutils-0.12a0.dist-info/WHEEL
cbutils-0.12a0.dist-info/metadata.json
cbutils-0.12a0.dist-info/top_level.txt
