Metadata-Version: 2.0
Name: cbutils
Version: 0.12a0
Summary: My utilities library
Home-page: https://github.com/caiobelfort/cbutils
Author: caiobelfort
Author-email: caiobelfort90@gmail.com
License: GPL
Platform: UNKNOWN
